{
  "UserAgent": "MobileHub/1.0",
  "Version": "1.0",
  "CredentialsProvider": {
    "CognitoIdentity": {
      "Default": {
        "PoolId": "us-east-1:8b0a197c-556c-4b11-bfbe-b8f3e75dafae",
        "Region": "us-east-1"
      }
    }
  },
  "IdentityManager": {
    "Default": {}
  },
  "DynamoDBObjectMapper": {
    "Default": {
      "Region": "us-east-1"
    }
  },
  "PinpointAnalytics": {
    "Default": {
      "AppId": "333e6ad5144f4253a8317a4f6e7494d1",
      "Region": "us-east-1"
    }
  },
  "PinpointTargeting": {
    "Default": {
      "Region": "us-east-1"
    }
  }
}